csplint.py
csplint-0.1.0.dist-info/entry_points.txt
csplint-0.1.0.dist-info/LICENSE
csplint-0.1.0.dist-info/WHEEL
csplint-0.1.0.dist-info/METADATA
csplint-0.1.0.dist-info/RECORD
