Metadata-Version: 2.1
Name: csplint
Version: 0.1.0
Summary: 
License: MIT
Author: Stanislav Zmiev
Author-email: szmiev2000@gmail.com
Requires-Python: >=3.10
Classifier: License :: OSI Approved :: MIT License
Classifier: Programming Language :: Python :: 3
Classifier: Programming Language :: Python :: 3.10
Classifier: Programming Language :: Python :: 3.11
Requires-Dist: tomli
